MANIFEST.in
README.md
setup.py
scanapi_pkg/__init__.py
scanapi_pkg/_scanapi.cpython-35m-x86_64-linux-gnu.so
scanapi_pkg/scanapi.py
scanapi_pkg_6.egg-info/PKG-INFO
scanapi_pkg_6.egg-info/SOURCES.txt
scanapi_pkg_6.egg-info/dependency_links.txt
scanapi_pkg_6.egg-info/top_level.txt