Metadata-Version: 2.1
Name: scanapi-pkg-6
Version: 0.0.1
Summary: A small example package
Home-page: https://github.com/pypa/example-project
Author: Example Author
Author-email: author@example.com
License: UNKNOWN
Platform: UNKNOWN
